{"animation":{"version":4,"name":"giro","duration":0.233333,"nodes":[{"name":"Armature","defaults":{"p":[0,0,0],"s":[1.06282,1.06282,1.06282]},"keys":[{"t":0,"r":[-4.32571e-06,1,2.7326e-16]},{"t":0.1,"r":[-4.32571e-06,154.857,2.7326e-16]},{"t":0.2,"r":[-4.32571e-06,308.714,2.7326e-16]},{"t":0.233333,"r":[-4.32571e-06,360,2.7326e-16]}]},{"name":"bone_root","defaults":{"p":[0,0,0],"r":[0,-0,0],"s":[1,1,1]},"keys":[{"t":0},{"t":0.1},{"t":0.2},{"t":0.233333}]},{"name":"Hips","defaults":{"p":[0,7.46,0],"r":[90,90,0],"s":[1,1,1]},"keys":[{"t":0},{"t":0.1},{"t":0.2},{"t":0.233333}]},{"name":"Spine","defaults":{"p":[2.99565e-07,-9.31323e-10,-1.44975],"r":[-95.7493,0.306872,90.1053],"s":[1,1,1]},"keys":[{"t":0},{"t":0.1},{"t":0.2},{"t":0.233333}]},{"name":"Spine1","defaults":{"p":[-2.45927e-09,0.779999,-4.57385e-08],"r":[-90,5.83634e-09,-1.00052e-08],"s":[1,1,1]},"keys":[{"t":0},{"t":0.1},{"t":0.2},{"t":0.233333}]},{"name":"Neck","defaults":{"p":[-4.51109e-09,-9.98425e-08,0.710002],"r":[90,2.50129e-09,3.91869e-08],"s":[1,1,1]},"keys":[{"t":0},{"t":0.1},{"t":0.2},{"t":0.233333}]},{"name":"Head","defaults":{"p":[2.61934e-10,0.0999995,-6.91689e-08],"r":[-2.93237,35.1595,-3.77555],"s":[1,1,1]},"keys":[{"t":0},{"t":0.1},{"t":0.2},{"t":0.233333}]},{"name":"HeadEnd","defaults":{"p":[4.47035e-08,5.45,8.19564e-08],"r":[2.66804e-07,-9.60495e-07,3.20165e-07],"s":[1,1,1]},"keys":[{"t":0},{"t":0.1},{"t":0.2},{"t":0.233333}]},{"name":"HeadFacial","defaults":{"p":[-3.78059e-08,0.249999,1.25321e-07],"r":[2.66804e-07,-9.60495e-07,3.20165e-07],"s":[1,1,1]},"keys":[{"t":0},{"t":0.1},{"t":0.2},{"t":0.233333}]},{"name":"HeadTop","defaults":{"p":[1.11759e-07,2.18,1.11759e-07],"r":[2.66804e-07,-9.60495e-07,3.20165e-07],"s":[1,1,1]},"keys":[{"t":0},{"t":0.1},{"t":0.2},{"t":0.233333}]},{"name":"LeftEar","defaults":{"p":[1.15,1.65,2.38419e-07],"r":[49.7065,38.8697,-16.1405],"s":[1,1,1]},"keys":[{"t":0},{"t":0.1},{"t":0.2},{"t":0.233333}]},{"name":"RightEar","defaults":{"p":[-1.15,1.65,9.68575e-08],"r":[49.7065,-38.8697,16.1405],"s":[1,1,1]},"keys":[{"t":0},{"t":0.1},{"t":0.2},{"t":0.233333}]},{"name":"LeftBrowA","defaults":{"p":[1.56,0.81,1.48],"r":[2.66804e-07,-9.60495e-07,3.20165e-07],"s":[1,1,1]},"keys":[{"t":0},{"t":0.1},{"t":0.2},{"t":0.233333}]},{"name":"RightBrowA","defaults":{"p":[-1.56,0.81,1.48],"r":[2.66804e-07,-9.60495e-07,3.20165e-07],"s":[1,1,1]},"keys":[{"t":0},{"t":0.1},{"t":0.2},{"t":0.233333}]},{"name":"CenterBrowA","defaults":{"p":[1.19209e-07,1.2,2.02],"r":[2.66804e-07,-9.60495e-07,3.20165e-07],"s":[1,1,1]},"keys":[{"t":0},{"t":0.1},{"t":0.2},{"t":0.233333}]},{"name":"Eyelid","defaults":{"p":[8.14034e-08,-2.0684e-06,1.25321e-07],"r":[90,-1.38738e-06,-1.28066e-06],"s":[1,1,1]},"keys":[{"t":0},{"t":0.1},{"t":0.2},{"t":0.233333}]},{"name":"EyelidA_C","defaults":{"p":[0,1.9,-1.1],"r":[2.66804e-07,3.20165e-07,9.60495e-07],"s":[1,1,1]},"keys":[{"t":0},{"t":0.1},{"t":0.2},{"t":0.233333}]},{"name":"EyelidA_L1","defaults":{"p":[1,1.6,-1.1],"r":[2.66804e-07,3.20165e-07,9.60495e-07],"s":[1,1,1]},"keys":[{"t":0},{"t":0.1},{"t":0.2},{"t":0.233333}]},{"name":"EyelidA_L2","defaults":{"p":[1.6,0.8,-1.2],"r":[4.26887e-07,3.73526e-07,1.33402e-07],"s":[1,1,1]},"keys":[{"t":0},{"t":0.1},{"t":0.2},{"t":0.233333}]},{"name":"EyelidA_R1","defaults":{"p":[-1,1.6,-1.1],"r":[2.66804e-07,3.20165e-07,9.60495e-07],"s":[1,1,1]},"keys":[{"t":0},{"t":0.1},{"t":0.2},{"t":0.233333}]},{"name":"EyelidA_R2","defaults":{"p":[-1.6,0.8,-1.2],"r":[4.26887e-07,3.73526e-07,1.33402e-07],"s":[1,1,1]},"keys":[{"t":0},{"t":0.1},{"t":0.2},{"t":0.233333}]},{"name":"EyelidB_C","defaults":{"p":[0,1.8,-0.999999],"r":[2.66804e-07,3.20165e-07,9.60495e-07],"s":[1,1,1]},"keys":[{"t":0},{"t":0.1},{"t":0.2},{"t":0.233333}]},{"name":"EyelidB_L1","defaults":{"p":[0.9,1.6,-0.899999],"r":[2.66804e-07,3.20165e-07,9.60495e-07],"s":[1,1,1]},"keys":[{"t":0},{"t":0.1},{"t":0.2},{"t":0.233333}]},{"name":"EyelidB_R1","defaults":{"p":[-0.9,1.6,-0.899998],"r":[2.66804e-07,3.20165e-07,9.60495e-07],"s":[1,1,1]},"keys":[{"t":0},{"t":0.1},{"t":0.2},{"t":0.233333}]},{"name":"Nose","defaults":{"p":[1.19209e-07,0.799999,2],"r":[2.66804e-07,-9.60495e-07,3.20165e-07],"s":[1,1,1]},"keys":[{"t":0},{"t":0.1},{"t":0.2},{"t":0.233333}]},{"name":"Cheek_L","defaults":{"p":[1.35,0.679997,0.96],"r":[2.66804e-07,-9.60495e-07,3.20165e-07],"s":[1,1,1]},"keys":[{"t":0},{"t":0.1},{"t":0.2},{"t":0.233333}]},{"name":"Cheek_R","defaults":{"p":[-1.35,0.679997,0.96],"r":[2.66804e-07,-9.60495e-07,3.20165e-07],"s":[1,1,1]},"keys":[{"t":0},{"t":0.1},{"t":0.2},{"t":0.233333}]},{"name":"Mouth","defaults":{"p":[1.3411e-07,0.549998,0.81],"r":[90,18,-90],"s":[1,1,1]},"keys":[{"t":0},{"t":0.1},{"t":0.2},{"t":0.233333}]},{"name":"Lip_CT1","defaults":{"p":[-0.079999,0.97,1.19209e-07],"r":[-108,90,0],"s":[1,1,1]},"keys":[{"t":0},{"t":0.1},{"t":0.2},{"t":0.233333}]},{"name":"Lip_CD1","defaults":{"p":[0.0500007,0.9,1.78814e-07],"r":[-108,90,0],"s":[1,1,1]},"keys":[{"t":0},{"t":0.1},{"t":0.2},{"t":0.233333}]},{"name":"Lip_LT1","defaults":{"p":[0.0300003,0.79,-0.45],"r":[-108,90,0],"s":[1,1,1]},"keys":[{"t":0},{"t":0.1},{"t":0.2},{"t":0.233333}]},{"name":"Lip_LD1","defaults":{"p":[0.0799999,0.78,-0.45],"r":[-108,90,0],"s":[1,1,1]},"keys":[{"t":0},{"t":0.1},{"t":0.2},{"t":0.233333}]},{"name":"Lip_RT1","defaults":{"p":[0.0299998,0.79,0.45],"r":[-108,90,0],"s":[1,1,1]},"keys":[{"t":0},{"t":0.1},{"t":0.2},{"t":0.233333}]},{"name":"Lip_RD1","defaults":{"p":[0.0799994,0.78,0.45],"r":[-108,90,0],"s":[1,1,1]},"keys":[{"t":0},{"t":0.1},{"t":0.2},{"t":0.233333}]},{"name":"Teeth_T1","defaults":{"p":[-0.0799979,0.0200002,4.47035e-08],"r":[2.00006,-90,0],"s":[1,1,1]},"keys":[{"t":0},{"t":0.1},{"t":0.2},{"t":0.233333}]},{"name":"Teeth_D1","defaults":{"p":[0.0800025,0.0300004,-2.98023e-08],"r":[2.00006,-90,0],"s":[1,1,1]},"keys":[{"t":0},{"t":0.1},{"t":0.2},{"t":0.233333}]},{"name":"CenterHairA0","defaults":{"p":[5.96046e-08,4.25,-1.05],"r":[-71,-2.97773e-07,9.36991e-07],"s":[1,1,1]},"keys":[{"t":0},{"t":0.1},{"t":0.2},{"t":0.233333}]},{"name":"CenterHairA1","defaults":{"p":[2.38419e-07,1.8,-1.99676e-06],"r":[-17,6.00339e-07,1.0968e-06],"s":[1,1,1]},"keys":[{"t":0},{"t":0.1},{"t":0.2},{"t":0.233333}]},{"name":"CenterHairDyn","defaults":{"p":[1.19209e-07,4,1.19209e-07],"r":[-2.56132e-06,2.13443e-07,-3.46846e-07],"s":[1,1,1]},"keys":[{"t":0},{"t":0.1},{"t":0.2},{"t":0.233333}]},{"name":"CenterHairB0","defaults":{"p":[0,1.75,-2.3],"r":[-106.3,-1.06706e-06,1.86887e-06],"s":[1,1,1]},"keys":[{"t":0},{"t":0.1},{"t":0.2},{"t":0.233333}]},{"name":"CenterHairB1","defaults":{"p":[0,2.2,-5.96046e-07],"r":[-20.2,-4.41564e-07,-1.24264e-06],"s":[1,1,1]},"keys":[{"t":0},{"t":0.1},{"t":0.2},{"t":0.233333}]},{"name":"CenterHairBDyn","defaults":{"p":[-4.76837e-07,2.4,-2.38419e-07],"r":[-2.17712e-05,2.13444e-07,8.53774e-07],"s":[1,1,1]},"keys":[{"t":0},{"t":0.1},{"t":0.2},{"t":0.233333}]},{"name":"LeftHairA0","defaults":{"p":[1.5,3.32,-0.9],"r":[-92,-15.5,-5.13024e-07],"s":[1,1,1]},"keys":[{"t":0},{"t":0.1},{"t":0.2},{"t":0.233333}]},{"name":"LeftHairA1","defaults":{"p":[2.65194e-07,2.4,1.41281e-06],"r":[-23.2,-2.02224e-06,4.4291e-07],"s":[1,1,1]},"keys":[{"t":0},{"t":0.1},{"t":0.2},{"t":0.233333}]},{"name":"LeftHairADyn","defaults":{"p":[-2.98023e-08,3.8,-6.70552e-07],"r":[-2.4546e-06,1.06722e-06,1.06722e-06],"s":[1,1,1]},"keys":[{"t":0},{"t":0.1},{"t":0.2},{"t":0.233333}]},{"name":"RightHairA0","defaults":{"p":[-1.5,3.32,-0.9],"r":[-92,15.5,1.81938e-06],"s":[1,1,1]},"keys":[{"t":0},{"t":0.1},{"t":0.2},{"t":0.233333}]},{"name":"RightHairA1","defaults":{"p":[0,2.4,-4.68455e-07],"r":[-23.2,3.16776e-06,2.93655e-06],"s":[1,1,1]},"keys":[{"t":0},{"t":0.1},{"t":0.2},{"t":0.233333}]},{"name":"RightHairADyn","defaults":{"p":[4.76837e-07,3.8,-1.19209e-06],"r":[-1.53679e-05,4.69576e-06,1.81427e-06],"s":[1,1,1]},"keys":[{"t":0},{"t":0.1},{"t":0.2},{"t":0.233333}]},{"name":"LeftHairB0","defaults":{"p":[1.65,1.6,-1.1],"r":[-136.139,-14.9992,-0.621163],"s":[1,1,1]},"keys":[{"t":0},{"t":0.1},{"t":0.2},{"t":0.233333}]},{"name":"LeftHairB1","defaults":{"p":[3.12924e-07,1.91,3.53903e-07],"r":[-5.99999,-4.41519e-06,1.51557e-06],"s":[1,1,1]},"keys":[{"t":0},{"t":0.1},{"t":0.2},{"t":0.233333}]},{"name":"LeftHairBDyn","defaults":{"p":[2.38419e-07,2.72,7.45058e-09],"r":[-5.22936e-06,6.4033e-07,-2.77476e-06],"s":[1,1,1]},"keys":[{"t":0},{"t":0.1},{"t":0.2},{"t":0.233333}]},{"name":"RightHairB0","defaults":{"p":[-1.65,1.6,-1.1],"r":[-136.139,14.9992,0.621165],"s":[1,1,1]},"keys":[{"t":0},{"t":0.1},{"t":0.2},{"t":0.233333}]},{"name":"RightHairB1","defaults":{"p":[-2.98023e-07,1.91,-8.9407e-07],"r":[-5.99999,5.29134e-06,-1.13343e-06],"s":[1,1,1]},"keys":[{"t":0},{"t":0.1},{"t":0.2},{"t":0.233333}]},{"name":"RightHairBDyn","defaults":{"p":[0,2.72,5.96046e-07],"r":[-4.69576e-06,6.4033e-07,1.92099e-06],"s":[1,1,1]},"keys":[{"t":0},{"t":0.1},{"t":0.2},{"t":0.233333}]},{"name":"LeftShoulder","defaults":{"p":[0.25,0.0499999,0.640002],"r":[78.8116,82.6218,-2.73617],"s":[1,1,1]},"keys":[{"t":0},{"t":0.1},{"t":0.2},{"t":0.233333}]},{"name":"LeftArmRoll","defaults":{"p":[-1.22935e-07,0.57,-2.23517e-08],"r":[4.53567e-07,-1.97435e-06,-4.26887e-07],"s":[1,1,1]},"keys":[{"t":0},{"t":0.1},{"t":0.2},{"t":0.233333}]},{"name":"LeftArm","defaults":{"p":[-1.22935e-07,0.57,-2.23517e-08],"r":[3.73526e-07,-2.13443e-06,-4.80248e-07],"s":[1,1,1]},"keys":[{"t":0},{"t":0.1},{"t":0.2},{"t":0.233333}]},{"name":"LeftForeArmRoll","defaults":{"p":[-9.574e-07,1.1,1.19209e-07],"r":[1.06722e-07,3.73526e-07,-8.00413e-07],"s":[1,1,1]},"keys":[{"t":0},{"t":0.1},{"t":0.2},{"t":0.233333}]},{"name":"LeftForeArm","defaults":{"p":[-2.12342e-07,1.46,8.9407e-08],"r":[1.06722e-07,3.73526e-07,-8.00413e-07],"s":[1,1,1]},"keys":[{"t":0},{"t":0.1},{"t":0.2},{"t":0.233333}]},{"name":"LeftHandRoll","defaults":{"p":[-1.2219e-06,2.14,5.96046e-08],"r":[5.8697e-07,90,0],"s":[1,1,1]},"keys":[{"t":0},{"t":0.1},{"t":0.2},{"t":0.233333}]},{"name":"LeftHand","defaults":{"p":[-1.2219e-06,2.14,5.96046e-08],"r":[6.43728,52.5877,8.10988],"s":[1,1,1]},"keys":[{"t":0},{"t":0.1},{"t":0.2},{"t":0.233333}]},{"name":"LeftHandEnd","defaults":{"p":[2.98023e-07,2,-1.19209e-07],"r":[4.26887e-07,2.93485e-07,-3.20165e-07],"s":[1,1,1]},"keys":[{"t":0},{"t":0.1},{"t":0.2},{"t":0.233333}]},{"name":"LeftHandItem","defaults":{"p":[7.15256e-07,1.45,0.3],"r":[4.26887e-07,2.93485e-07,-3.20165e-07],"s":[1,1,1]},"keys":[{"t":0},{"t":0.1},{"t":0.2},{"t":0.233333}]},{"name":"LeftHandThumb1","defaults":{"p":[-0.55,0.649999,0.0299996],"r":[24.5863,37.1585,73.9871],"s":[1,1,1]},"keys":[{"t":0},{"t":0.1},{"t":0.2},{"t":0.233333}]},{"name":"LeftHandThumb2","defaults":{"p":[1.63913e-07,0.530002,2.00234e-08],"r":[-3.59652e-05,0.000101386,4.65306e-05],"s":[1,1,1]},"keys":[{"t":0},{"t":0.1},{"t":0.2},{"t":0.233333}]},{"name":"LeftHandThumb3","defaults":{"p":[1.19209e-07,0.67,1.28709e-06],"r":[7.37448e-05,-0.000169901,-8.92194e-05],"s":[1,1,1]},"keys":[{"t":0},{"t":0.1},{"t":0.2},{"t":0.233333}]},{"name":"LeftHandThumbEnd","defaults":{"p":[-5.96046e-08,0.68,1.06171e-06],"r":[-5.59221e-05,8.87925e-05,4.31155e-05],"s":[1,1,1]},"keys":[{"t":0},{"t":0.1},{"t":0.2},{"t":0.233333}]},{"name":"LeftHandIndex1","defaults":{"p":[-0.56,1.69,-0.220001],"r":[1.69221e-07,-4.54961e-06,12],"s":[1,1,1]},"keys":[{"t":0},{"t":0.1},{"t":0.2},{"t":0.233333}]},{"name":"LeftHandIndex2","defaults":{"p":[0,0.660001,-1.63913e-06],"r":[-0.000101919,1.56881e-05,1.70755e-05],"s":[1,1,1]},"keys":[{"t":0},{"t":0.1},{"t":0.2},{"t":0.233333}]},{"name":"LeftHandIndex3","defaults":{"p":[-3.57628e-07,0.539999,3.27826e-07],"r":[0.000180787,-1.00318e-05,-7.15037e-06],"s":[1,1,1]},"keys":[{"t":0},{"t":0.1},{"t":0.2},{"t":0.233333}]},{"name":"LeftHandIndexEnd","defaults":{"p":[-3.57628e-07,0.68,-4.47035e-07],"r":[-8.05749e-05,-6.93692e-06,-8.75118e-06],"s":[1,1,1]},"keys":[{"t":0},{"t":0.1},{"t":0.2},{"t":0.233333}]},{"name":"LeftHandMiddle1","defaults":{"p":[-0.0699996,1.73,-0.32],"r":[6.4033e-07,2.93485e-07,-2.13443e-07],"s":[1,1,1]},"keys":[{"t":0},{"t":0.1},{"t":0.2},{"t":0.233333}]},{"name":"LeftHandMiddle2","defaults":{"p":[-1.19209e-07,0.789999,8.34465e-07],"r":[4.26887e-07,1.20062e-06,-1.06722e-07],"s":[1,1,1]},"keys":[{"t":0},{"t":0.1},{"t":0.2},{"t":0.233333}]},{"name":"LeftHandMiddle3","defaults":{"p":[-6.85453e-07,0.590001,-1.78814e-07],"r":[-4.26887e-07,2.13443e-06,3.20165e-07],"s":[1,1,1]},"keys":[{"t":0},{"t":0.1},{"t":0.2},{"t":0.233333}]},{"name":"LeftHandMiddleEnd","defaults":{"p":[4.47035e-07,0.729999,0],"r":[2.13443e-07,-1.2273e-06,-2.77305e-14],"s":[1,1,1]},"keys":[{"t":0},{"t":0.1},{"t":0.2},{"t":0.233333}]},{"name":"LeftHandRing1","defaults":{"p":[0.45,1.72,-0.29],"r":[1.22873e-06,-8.61081e-06,-12],"s":[1,1,1]},"keys":[{"t":0},{"t":0.1},{"t":0.2},{"t":0.233333}]},{"name":"LeftHandRing2","defaults":{"p":[-1.19209e-06,0.68,0],"r":[-9.66899e-05,-6.24323e-06,-7.73732e-06],"s":[1,1,1]},"keys":[{"t":0},{"t":0.1},{"t":0.2},{"t":0.233333}]},{"name":"LeftHandRing3","defaults":{"p":[4.76837e-07,0.56,-1.19209e-07],"r":[0.000176998,1.66486e-05,1.89431e-05],"s":[1,1,1]},"keys":[{"t":0},{"t":0.1},{"t":0.2},{"t":0.233333}]},{"name":"LeftHandRingEnd","defaults":{"p":[0,0.679999,-2.38419e-07],"r":[-8.06283e-05,5.33608e-07,-1.06722e-06],"s":[1,1,1]},"keys":[{"t":0},{"t":0.1},{"t":0.2},{"t":0.233333}]},{"name":"LeftHandPinky1","defaults":{"p":[0.87,1.61,-0.2],"r":[4.9389e-07,-5.47219e-06,-24],"s":[1,1,1]},"keys":[{"t":0},{"t":0.1},{"t":0.2},{"t":0.233333}]},{"name":"LeftHandPinky2","defaults":{"p":[2.38419e-07,0.45,-4.76837e-07],"r":[-0.000126358,-2.32654e-05,-2.43325e-05],"s":[1,1,1]},"keys":[{"t":0},{"t":0.1},{"t":0.2},{"t":0.233333}]},{"name":"LeftHandPinky3","defaults":{"p":[-7.15256e-07,0.430001,4.76837e-07],"r":[0.000127639,6.83018e-05,6.78751e-05],"s":[1,1,1]},"keys":[{"t":0},{"t":0.1},{"t":0.2},{"t":0.233333}]},{"name":"LeftHandPinkyEnd","defaults":{"p":[4.76837e-07,0.62,1.19209e-07],"r":[8.53786e-07,-3.79929e-05,-3.82064e-05],"s":[1,1,1]},"keys":[{"t":0},{"t":0.1},{"t":0.2},{"t":0.233333}]},{"name":"RightShoulder","defaults":{"p":[-0.25,0.05,0.640002],"r":[92.2138,-94.0875,-2.586],"s":[1,1,1]},"keys":[{"t":0},{"t":0.1},{"t":0.2},{"t":0.233333}]},{"name":"RightArmRoll","defaults":{"p":[-2.90573e-07,0.57,-8.14907e-08],"r":[-6.67011e-09,2.35955e-06,-2.18863e-07],"s":[1,1,1]},"keys":[{"t":0},{"t":0.1},{"t":0.2},{"t":0.233333}]},{"name":"RightArm","defaults":{"p":[-2.90573e-07,0.57,-8.14907e-08],"r":[-3.66856e-08,2.1411e-06,-2.18238e-07],"s":[1,1,1]},"keys":[{"t":0},{"t":0.1},{"t":0.2},{"t":0.233333}]},{"name":"RightForeArmRoll","defaults":{"p":[-1.24611e-06,1.1,-1.86265e-09],"r":[-1.00052e-08,-2.23449e-07,-2.15528e-07],"s":[1,1,1]},"keys":[{"t":0},{"t":0.1},{"t":0.2},{"t":0.233333}]},{"name":"RightForeArm","defaults":{"p":[-8.9407e-08,1.46,8.9407e-08],"r":[4.66908e-08,-2.26784e-07,-4.28554e-07],"s":[1,1,1]},"keys":[{"t":0},{"t":0.1},{"t":0.2},{"t":0.233333}]},{"name":"RightHandRoll","defaults":{"p":[-1.07661e-06,2.14,1.45286e-07],"r":[-4.79415e-09,-90,0],"s":[1,1,1]},"keys":[{"t":0},{"t":0.1},{"t":0.2},{"t":0.233333}]},{"name":"RightHand","defaults":{"p":[-1.07661e-06,2.14,1.45286e-07],"r":[-11.0569,-47.4689,16.4505],"s":[1,1,1]},"keys":[{"t":0},{"t":0.1},{"t":0.2},{"t":0.233333}]},{"name":"RightHandEnd","defaults":{"p":[-5.96046e-08,2,-9.53674e-07],"r":[8.53774e-07,1.33402e-06,-2.13443e-07],"s":[1,1,1]},"keys":[{"t":0},{"t":0.1},{"t":0.2},{"t":0.233333}]},{"name":"RightHandItem","defaults":{"p":[1.86265e-07,1.45,0.299999],"r":[8.53774e-07,1.33402e-06,-2.13443e-07],"s":[1,1,1]},"keys":[{"t":0},{"t":0.1},{"t":0.2},{"t":0.233333}]},{"name":"RightHandThumb1","defaults":{"p":[0.549999,0.65,0.0299994],"r":[24.5863,-37.1585,-73.9871],"s":[1,1,1]},"keys":[{"t":0},{"t":0.1},{"t":0.2},{"t":0.233333}]},{"name":"RightHandThumb2","defaults":{"p":[-1.49012e-07,0.530002,-1.16229e-06],"r":[-3.5645e-05,-0.000101386,-4.51432e-05],"s":[1,1,1]},"keys":[{"t":0},{"t":0.1},{"t":0.2},{"t":0.233333}]},{"name":"RightHandThumb3","defaults":{"p":[1.78814e-07,0.669999,4.91738e-07],"r":[7.25709e-05,0.000169261,8.59644e-05],"s":[1,1,1]},"keys":[{"t":0},{"t":0.1},{"t":0.2},{"t":0.233333}]},{"name":"RightHandThumbEnd","defaults":{"p":[5.96046e-08,0.68,8.9407e-08],"r":[-5.50684e-05,-8.81522e-05,-4.17815e-05],"s":[1,1,1]},"keys":[{"t":0},{"t":0.1},{"t":0.2},{"t":0.233333}]},{"name":"RightHandIndex1","defaults":{"p":[0.56,1.69,-0.220001],"r":[8.23703e-08,5.88924e-06,-12],"s":[1,1,1]},"keys":[{"t":0},{"t":0.1},{"t":0.2},{"t":0.233333}]},{"name":"RightHandIndex2","defaults":{"p":[-2.08616e-07,0.660002,2.08616e-07],"r":[-0.000101813,-1.81961e-05,-1.7449e-05],"s":[1,1,1]},"keys":[{"t":0},{"t":0.1},{"t":0.2},{"t":0.233333}]},{"name":"RightHandIndex3","defaults":{"p":[6.33299e-07,0.54,-5.88596e-07],"r":[0.00018164,1.11858e-05,7.5239e-06],"s":[1,1,1]},"keys":[{"t":0},{"t":0.1},{"t":0.2},{"t":0.233333}]},{"name":"RightHandIndexEnd","defaults":{"p":[-3.05474e-07,0.68,-1.56462e-07],"r":[-8.00946e-05,1.05721e-05,8.91126e-06],"s":[1,1,1]},"keys":[{"t":0},{"t":0.1},{"t":0.2},{"t":0.233333}]},{"name":"RightHandMiddle1","defaults":{"p":[0.0700002,1.73,-0.32],"r":[4.26887e-07,1.33402e-06,-2.13444e-07],"s":[1,1,1]},"keys":[{"t":0},{"t":0.1},{"t":0.2},{"t":0.233333}]},{"name":"RightHandMiddle2","defaults":{"p":[-1.2815e-06,0.79,-2.38419e-07],"r":[2.13443e-07,1.44074e-06,4.26887e-07],"s":[1,1,1]},"keys":[{"t":0},{"t":0.1},{"t":0.2},{"t":0.233333}]},{"name":"RightHandMiddle3","defaults":{"p":[-3.27826e-07,0.590001,-1.78814e-07],"r":[2.13443e-07,1.44074e-06,4.26887e-07],"s":[1,1,1]},"keys":[{"t":0},{"t":0.1},{"t":0.2},{"t":0.233333}]},{"name":"RightHandMiddleEnd","defaults":{"p":[-8.34465e-07,0.730001,-5.96046e-07],"r":[2.13443e-07,1.44074e-06,4.26887e-07],"s":[1,1,1]},"keys":[{"t":0},{"t":0.1},{"t":0.2},{"t":0.233333}]},{"name":"RightHandRing1","defaults":{"p":[-0.449999,1.72,-0.290001],"r":[-7.45216e-08,9.55704e-06,12],"s":[1,1,1]},"keys":[{"t":0},{"t":0.1},{"t":0.2},{"t":0.233333}]},{"name":"RightHandRing2","defaults":{"p":[-1.01328e-06,0.680001,2.98023e-07],"r":[-9.75436e-05,5.01593e-06,8.96462e-06],"s":[1,1,1]},"keys":[{"t":0},{"t":0.1},{"t":0.2},{"t":0.233333}]},{"name":"RightHandRing3","defaults":{"p":[-5.96046e-08,0.56,-3.57628e-07],"r":[0.000178652,-1.953e-05,-1.96368e-05],"s":[1,1,1]},"keys":[{"t":0},{"t":0.1},{"t":0.2},{"t":0.233333}]},{"name":"RightHandRingEnd","defaults":{"p":[-4.17233e-07,0.680001,6.55651e-07],"r":[-8.15354e-05,6.4033e-07,-4.55614e-13],"s":[1,1,1]},"keys":[{"t":0},{"t":0.1},{"t":0.2},{"t":0.233333}]},{"name":"RightHandPinky1","defaults":{"p":[-0.87,1.61,-0.2],"r":[6.43397e-07,7.22511e-06,24],"s":[1,1,1]},"keys":[{"t":0},{"t":0.1},{"t":0.2},{"t":0.233333}]},{"name":"RightHandPinky2","defaults":{"p":[-5.36442e-07,0.449999,-1.19209e-07],"r":[-0.000127319,2.40124e-05,1.96368e-05],"s":[1,1,1]},"keys":[{"t":0},{"t":0.1},{"t":0.2},{"t":0.233333}]},{"name":"RightHandPinky3","defaults":{"p":[2.98023e-07,0.43,8.9407e-08],"r":[0.000126252,-6.51002e-05,-6.70213e-05],"s":[1,1,1]},"keys":[{"t":0},{"t":0.1},{"t":0.2},{"t":0.233333}]},{"name":"RightHandPinkyEnd","defaults":{"p":[-2.98023e-07,0.62,-1.78814e-07],"r":[-1.28065e-06,3.51114e-05,4.18349e-05],"s":[1,1,1]},"keys":[{"t":0},{"t":0.1},{"t":0.2},{"t":0.233333}]},{"name":"LeftHairC0","defaults":{"p":[0.61,0.79,-0.0999987],"r":[-34,-18,5.06446e-06],"s":[1,1,1]},"keys":[{"t":0},{"t":0.1},{"t":0.2},{"t":0.233333}]},{"name":"LeftHairC1","defaults":{"p":[3.35276e-08,1.15,4.02331e-07],"r":[-28,-2.60359e-05,3.15148e-05],"s":[1,1,1]},"keys":[{"t":0},{"t":0.1},{"t":0.2},{"t":0.233333}]},{"name":"LeftHairCDyn","defaults":{"p":[-1.2666e-07,1.32,5.96046e-08],"r":[2.62535e-05,1.19528e-05,-1.00318e-05],"s":[1,1,1]},"keys":[{"t":0},{"t":0.1},{"t":0.2},{"t":0.233333}]},{"name":"RightHairC0","defaults":{"p":[-0.61,0.79,-0.0999978],"r":[-34,18,-4.94373e-06],"s":[1,1,1]},"keys":[{"t":0},{"t":0.1},{"t":0.2},{"t":0.233333}]},{"name":"RightHairC1","defaults":{"p":[2.12342e-07,1.15,1.19209e-07],"r":[-28,2.85434e-05,-3.14599e-05],"s":[1,1,1]},"keys":[{"t":0},{"t":0.1},{"t":0.2},{"t":0.233333}]},{"name":"RightHairCDyn","defaults":{"p":[0,1.32,1.49012e-08],"r":[2.77476e-05,-1.15259e-05,9.87176e-06],"s":[1,1,1]},"keys":[{"t":0},{"t":0.1},{"t":0.2},{"t":0.233333}]},{"name":"Carabiner","defaults":{"p":[-3.49246e-09,0.00999926,1.09],"r":[-180,-8.64279e-06,-6.25438e-09],"s":[1,1,1]},"keys":[{"t":0},{"t":0.1},{"t":0.2},{"t":0.233333}]},{"name":"Linebase","defaults":{"p":[-2.56114e-09,0.890001,2.12954e-08],"r":[-7.24772e-06,-3.64855e-06,1.41742e-08],"s":[1,1,1]},"keys":[{"t":0},{"t":0.1},{"t":0.2},{"t":0.233333}]},{"name":"Pelvis","defaults":{"p":[2.99565e-07,-9.31323e-10,-1.44975],"r":[90,-0,90],"s":[1,1,1]},"keys":[{"t":0},{"t":0.1},{"t":0.2},{"t":0.233333}]},{"name":"PelvisEnd","defaults":{"p":[1.37872e-17,1.28,2.96035e-17],"r":[-1.5575e-14,-3.18772e-06,4.78857e-22],"s":[1,1,1]},"keys":[{"t":0},{"t":0.1},{"t":0.2},{"t":0.233333}]},{"name":"LeftUpLeg","defaults":{"p":[0.59,0.559999,-0.04],"r":[7.31328,0.22386,-6.20291],"s":[0.999999,0.999997,0.999999]},"keys":[{"t":0},{"t":0.1},{"t":0.2},{"t":0.233333}]},{"name":"LeftLegRoll","defaults":{"p":[2.04192e-07,1.74,-7.17118e-08],"r":[1.23397e-07,6.6701e-09,7.82071e-07],"s":[0.999999,0.999998,0.999999]},"keys":[{"t":0},{"t":0.1},{"t":0.2},{"t":0.233333}]},{"name":"LeftLeg","defaults":{"p":[2.09024e-07,2.17,-1.60187e-07],"r":[9.67167e-08,3.33506e-08,-7.18705e-07],"s":[0.999999,0.999998,0.999998]},"keys":[{"t":0},{"t":0.1},{"t":0.2},{"t":0.233333}]},{"name":"LeftFootRoll","defaults":{"p":[9.17353e-08,2.67,2.98023e-08],"r":[-5.89401e-07,-5.70413e-09,8],"s":[1,1,1]},"keys":[{"t":0},{"t":0.1},{"t":0.2},{"t":0.233333}]},{"name":"LeftFoot","defaults":{"p":[9.17353e-08,2.67,2.98023e-08],"r":[-67.1476,-4.22252,7.03658],"s":[1,1,1]},"keys":[{"t":0},{"t":0.1},{"t":0.2},{"t":0.233333}]},{"name":"LeftToeBase","defaults":{"p":[1.11759e-08,2.07,1.4],"r":[-1.20062e-06,-8.93794e-07,1.80093e-07],"s":[1,1,1]},"keys":[{"t":0},{"t":0.1},{"t":0.2},{"t":0.233333}]},{"name":"LeftToeBaseEnd","defaults":{"p":[-3.63216e-08,1.8,-5.21541e-08],"r":[-1.2273e-06,1.33402e-08,1.80093e-07],"s":[1,1,1]},"keys":[{"t":0},{"t":0.1},{"t":0.2},{"t":0.233333}]},{"name":"RightUpLeg","defaults":{"p":[-0.59,0.559999,-0.04],"r":[-6.28632,1.48295,7.32725],"s":[0.999999,0.999997,0.999999]},"keys":[{"t":0},{"t":0.1},{"t":0.2},{"t":0.233333}]},{"name":"RightLegRoll","defaults":{"p":[2.00234e-08,1.74,2.32831e-08],"r":[-2.9015e-07,1.33402e-07,-5.4695e-07],"s":[0.999999,0.999998,0.999998]},"keys":[{"t":0},{"t":0.1},{"t":0.2},{"t":0.233333}]},{"name":"RightLeg","defaults":{"p":[-3.11993e-08,2.17,6.23986e-08],"r":[-7.67064e-08,1.60083e-07,1.20062e-06],"s":[0.999999,0.999998,0.999998]},"keys":[{"t":0},{"t":0.1},{"t":0.2},{"t":0.233333}]},{"name":"RightFootRoll","defaults":{"p":[1.02445e-08,2.67,3.72529e-08],"r":[-4.94005e-07,-3.45442e-08,-8],"s":[1,1,1]},"keys":[{"t":0},{"t":0.1},{"t":0.2},{"t":0.233333}]},{"name":"RightFoot","defaults":{"p":[1.02445e-08,2.67,3.72529e-08],"r":[-53.8877,-13.8811,-10.2148],"s":[1,1,1]},"keys":[{"t":0},{"t":0.1},{"t":0.2},{"t":0.233333}]},{"name":"RightToeBase","defaults":{"p":[1.63913e-07,2.07,1.4],"r":[-3.73526e-07,6.93691e-07,-8.53774e-07],"s":[1,1,1]},"keys":[{"t":0},{"t":0.1},{"t":0.2},{"t":0.233333}]},{"name":"RightToeBaseEnd","defaults":{"p":[1.39698e-08,1.8,2.16067e-07],"r":[5.86969e-07,5.33609e-08,-6.4033e-07],"s":[1,1,1]},"keys":[{"t":0},{"t":0.1},{"t":0.2},{"t":0.233333}]},{"name":"Tail0","defaults":{"p":[1.39861e-08,0.76,0.44],"r":[66,1.82123e-06,-3.71294e-13],"s":[1,1,1]},"keys":[{"t":0},{"t":0.1},{"t":0.2},{"t":0.233333}]},{"name":"Tail1","defaults":{"p":[-1.02842e-16,0.91,6.55651e-07],"r":[19,4.58e-13,3.05333e-13],"s":[1,1,1]},"keys":[{"t":0},{"t":0.1},{"t":0.2},{"t":0.233333}]},{"name":"TailEnd","defaults":{"p":[-5.55318e-17,1.1,-1.49012e-08],"r":[-2.13443e-07,-9.97169e-20,2.35074e-20],"s":[1,1,1]},"keys":[{"t":0},{"t":0.1},{"t":0.2},{"t":0.233333}]},{"name":"Bag_L","defaults":{"p":[0.78,0.67,0.55],"r":[-90,-135,-1.15379e-05],"s":[1,1,1]},"keys":[{"t":0},{"t":0.1},{"t":0.2},{"t":0.233333}]},{"name":"Bag_R","defaults":{"p":[-0.78,0.67,0.55],"r":[-90,135,1.15379e-05],"s":[1,1,1]},"keys":[{"t":0},{"t":0.1},{"t":0.2},{"t":0.233333}]}]}}